LICENSE
MANIFEST.in
README.md
requirements.txt
setup.py
tests/__init__.py
tests/process_test.py
tsuniverse/__init__.py
tsuniverse/distance_correlation_process.py
tsuniverse/hsic_process.py
tsuniverse/kendall_process.py
tsuniverse/mutual_information_process.py
tsuniverse/pearson_process.py
tsuniverse/process.py
tsuniverse/spearman_process.py
tsuniverse/stumpy_process.py
tsuniverse.egg-info/PKG-INFO
tsuniverse.egg-info/SOURCES.txt
tsuniverse.egg-info/dependency_links.txt
tsuniverse.egg-info/not-zip-safe
tsuniverse.egg-info/requires.txt
tsuniverse.egg-info/top_level.txt