Metadata-Version: 2.1
Name: tsuniverse
Version: 0.0.12
Summary: A library for efficiently processing a time series universe to determine causal features.
Home-page: https://github.com/8W9aG/tsuniverse
Author: Will Sackfield
Author-email: will.sackfield@gmail.com
License: MIT
Keywords: features,timeseries
Classifier: License :: OSI Approved :: MIT License
Classifier: Programming Language :: Python :: 3
License-File: LICENSE
Requires-Dist: pandas>=2.2.3
Requires-Dist: pyarrow>=19.0.1
Requires-Dist: scikit-learn>=1.6.1
Requires-Dist: timeseriesfeatures>=0.1.2
Requires-Dist: scipy>=1.15.3
Requires-Dist: dcor>=0.6
Requires-Dist: numpy>=1.26.4
Requires-Dist: pyHSICLasso>=1.4.2
Requires-Dist: stumpy>=1.13.0
